{
    "id": "12200",
    "condition": "2",
    "results": {
        "study": [
            [
                "trial",
                "block",
                "stimId",
                "category",
                "response",
                "rt"
            ],
            [
                0,
                0,
                "A50",
                "Alpha",
                "a",
                3659
            ],
            [
                1,
                0,
                "A250",
                "Alpha",
                "a",
                4363
            ],
            [
                2,
                0,
                "A150",
                "Alpha",
                "a",
                2396
            ],
            [
                3,
                0,
                "A350",
                "Alpha",
                "a",
                2259
            ],
            [
                4,
                0,
                "A450",
                "Alpha",
                "a",
                1698
            ],
            [
                0,
                1,
                "A250",
                "Alpha",
                "a",
                2106
            ],
            [
                1,
                1,
                "A150",
                "Alpha",
                "a",
                1822
            ],
            [
                2,
                1,
                "A50",
                "Alpha",
                "a",
                1539
            ],
            [
                3,
                1,
                "A450",
                "Alpha",
                "a",
                1350
            ],
            [
                4,
                1,
                "A350",
                "Alpha",
                "a",
                1439
            ],
            [
                0,
                2,
                "A50",
                "Alpha",
                "a",
                1387
            ],
            [
                1,
                2,
                "A450",
                "Alpha",
                "a",
                1484
            ],
            [
                2,
                2,
                "A250",
                "Alpha",
                "a",
                1495
            ],
            [
                3,
                2,
                "A350",
                "Alpha",
                "a",
                1474
            ],
            [
                4,
                2,
                "A150",
                "Alpha",
                "a",
                1383
            ],
            [
                0,
                3,
                "A50",
                "Alpha",
                "a",
                1445
            ],
            [
                1,
                3,
                "A150",
                "Alpha",
                "a",
                1761
            ],
            [
                2,
                3,
                "A350",
                "Alpha",
                "a",
                1428
            ],
            [
                3,
                3,
                "A250",
                "Alpha",
                "a",
                2121
            ],
            [
                4,
                3,
                "A450",
                "Alpha",
                "a",
                1935
            ],
            [
                0,
                4,
                "A350",
                "Alpha",
                "a",
                1766
            ],
            [
                1,
                4,
                "A150",
                "Alpha",
                "a",
                5143
            ],
            [
                2,
                4,
                "A450",
                "Alpha",
                "a",
                1134
            ],
            [
                3,
                4,
                "A250",
                "Alpha",
                "a",
                1160
            ],
            [
                4,
                4,
                "A50",
                "Alpha",
                "a",
                1288
            ]
        ],
        "typicality1": [
            [
                "trial",
                "block",
                "stimId",
                "category",
                "response",
                "rt"
            ],
            [
                0,
                0,
                "A250",
                "Alpha",
                6,
                13387
            ],
            [
                1,
                0,
                "A150",
                "Alpha",
                6,
                6624
            ],
            [
                2,
                0,
                "A450",
                "Alpha",
                5,
                9469
            ],
            [
                3,
                0,
                "A350",
                "Alpha",
                6,
                3653
            ],
            [
                4,
                0,
                "A50",
                "Alpha",
                6,
                3418
            ]
        ],
        "trainPhase": [
            [
                "trial",
                "block",
                "stimId",
                "category",
                "response",
                "accuracy",
                "rt"
            ],
            [
                0,
                0,
                "B550",
                "Beta",
                "Alpha",
                false,
                2592
            ],
            [
                1,
                0,
                "B850",
                "Beta",
                "Beta",
                true,
                2902
            ],
            [
                2,
                0,
                "A150",
                "Alpha",
                "Beta",
                false,
                1647
            ],
            [
                3,
                0,
                "A50",
                "Alpha",
                "Gamma",
                false,
                2883
            ],
            [
                4,
                0,
                "C1150",
                "Gamma",
                "Gamma",
                true,
                1445
            ],
            [
                5,
                0,
                "A250",
                "Alpha",
                "Beta",
                false,
                1003
            ],
            [
                6,
                0,
                "B750",
                "Beta",
                "Beta",
                true,
                1815
            ],
            [
                7,
                0,
                "B650",
                "Beta",
                "Beta",
                true,
                2150
            ],
            [
                8,
                0,
                "C1250",
                "Gamma",
                "Gamma",
                true,
                1340
            ],
            [
                9,
                0,
                "C1350",
                "Gamma",
                "Gamma",
                true,
                1489
            ],
            [
                10,
                0,
                "A350",
                "Alpha",
                "Alpha",
                true,
                4193
            ],
            [
                11,
                0,
                "B950",
                "Beta",
                "Beta",
                true,
                1619
            ],
            [
                12,
                0,
                "C1450",
                "Gamma",
                "Gamma",
                true,
                1158
            ],
            [
                13,
                0,
                "A450",
                "Alpha",
                "Alpha",
                true,
                990
            ],
            [
                14,
                0,
                "C1050",
                "Gamma",
                "Beta",
                false,
                1421
            ],
            [
                0,
                1,
                "A350",
                "Alpha",
                "Alpha",
                true,
                1454
            ],
            [
                1,
                1,
                "B750",
                "Beta",
                "Beta",
                true,
                1667
            ],
            [
                2,
                1,
                "C1250",
                "Gamma",
                "Gamma",
                true,
                1398
            ],
            [
                3,
                1,
                "C1450",
                "Gamma",
                "Gamma",
                true,
                1236
            ],
            [
                4,
                1,
                "B550",
                "Beta",
                "Beta",
                true,
                1277
            ],
            [
                5,
                1,
                "A250",
                "Alpha",
                "Alpha",
                true,
                997
            ],
            [
                6,
                1,
                "C1050",
                "Gamma",
                "Beta",
                false,
                1080
            ],
            [
                7,
                1,
                "A50",
                "Alpha",
                "Alpha",
                true,
                1189
            ],
            [
                8,
                1,
                "C1150",
                "Gamma",
                "Gamma",
                true,
                1030
            ],
            [
                9,
                1,
                "B650",
                "Beta",
                "Beta",
                true,
                1364
            ],
            [
                10,
                1,
                "B850",
                "Beta",
                "Gamma",
                false,
                1404
            ],
            [
                11,
                1,
                "C1350",
                "Gamma",
                "Gamma",
                true,
                1181
            ],
            [
                12,
                1,
                "B950",
                "Beta",
                "Gamma",
                false,
                1524
            ],
            [
                13,
                1,
                "A150",
                "Alpha",
                "Alpha",
                true,
                1077
            ],
            [
                14,
                1,
                "A450",
                "Alpha",
                "Alpha",
                true,
                2557
            ],
            [
                0,
                2,
                "B950",
                "Beta",
                "Beta",
                true,
                933
            ],
            [
                1,
                2,
                "B550",
                "Beta",
                "Beta",
                true,
                998
            ],
            [
                2,
                2,
                "A50",
                "Alpha",
                "Alpha",
                true,
                1294
            ],
            [
                3,
                2,
                "A250",
                "Alpha",
                "Alpha",
                true,
                1261
            ],
            [
                4,
                2,
                "A350",
                "Alpha",
                "Alpha",
                true,
                1398
            ],
            [
                5,
                2,
                "A450",
                "Alpha",
                "Alpha",
                true,
                1141
            ],
            [
                6,
                2,
                "B850",
                "Beta",
                "Beta",
                true,
                1021
            ],
            [
                7,
                2,
                "B750",
                "Beta",
                "Beta",
                true,
                964
            ],
            [
                8,
                2,
                "A150",
                "Alpha",
                "Alpha",
                true,
                1190
            ],
            [
                9,
                2,
                "C1350",
                "Gamma",
                "Gamma",
                true,
                1182
            ],
            [
                10,
                2,
                "C1250",
                "Gamma",
                "Gamma",
                true,
                1235
            ],
            [
                11,
                2,
                "C1050",
                "Gamma",
                "Gamma",
                true,
                1522
            ],
            [
                12,
                2,
                "B650",
                "Beta",
                "Beta",
                true,
                1310
            ],
            [
                13,
                2,
                "C1450",
                "Gamma",
                "Gamma",
                true,
                1237
            ],
            [
                14,
                2,
                "C1150",
                "Gamma",
                "Gamma",
                true,
                1729
            ],
            [
                0,
                3,
                "A150",
                "Alpha",
                "Alpha",
                true,
                1131
            ],
            [
                1,
                3,
                "C1350",
                "Gamma",
                "Gamma",
                true,
                4377
            ],
            [
                2,
                3,
                "A450",
                "Alpha",
                "Beta",
                false,
                1406
            ],
            [
                3,
                3,
                "A50",
                "Alpha",
                "Alpha",
                true,
                864
            ],
            [
                4,
                3,
                "C1150",
                "Gamma",
                "Gamma",
                true,
                1686
            ],
            [
                5,
                3,
                "B550",
                "Beta",
                "Beta",
                true,
                786
            ],
            [
                6,
                3,
                "A350",
                "Alpha",
                "Alpha",
                true,
                1407
            ],
            [
                7,
                3,
                "B950",
                "Beta",
                "Beta",
                true,
                2277
            ],
            [
                8,
                3,
                "C1450",
                "Gamma",
                "Gamma",
                true,
                1093
            ],
            [
                9,
                3,
                "B750",
                "Beta",
                "Beta",
                true,
                978
            ],
            [
                10,
                3,
                "A250",
                "Alpha",
                "Alpha",
                true,
                1326
            ],
            [
                11,
                3,
                "B850",
                "Beta",
                "Beta",
                true,
                1098
            ],
            [
                12,
                3,
                "C1250",
                "Gamma",
                "Gamma",
                true,
                1261
            ],
            [
                13,
                3,
                "B650",
                "Beta",
                "Beta",
                true,
                1162
            ],
            [
                14,
                3,
                "C1050",
                "Gamma",
                "Gamma",
                true,
                1517
            ],
            [
                0,
                4,
                "C1150",
                "Gamma",
                "Gamma",
                true,
                1099
            ],
            [
                1,
                4,
                "A250",
                "Alpha",
                "Alpha",
                true,
                1045
            ],
            [
                2,
                4,
                "A450",
                "Alpha",
                "Beta",
                false,
                1165
            ],
            [
                3,
                4,
                "B950",
                "Beta",
                "Beta",
                true,
                1093
            ],
            [
                4,
                4,
                "C1250",
                "Gamma",
                "Gamma",
                true,
                947
            ],
            [
                5,
                4,
                "C1050",
                "Gamma",
                "Beta",
                false,
                1278
            ],
            [
                6,
                4,
                "C1450",
                "Gamma",
                "Gamma",
                true,
                1046
            ],
            [
                7,
                4,
                "B650",
                "Beta",
                "Beta",
                true,
                1245
            ],
            [
                8,
                4,
                "A150",
                "Alpha",
                "Alpha",
                true,
                1246
            ],
            [
                9,
                4,
                "B850",
                "Beta",
                "Beta",
                true,
                1128
            ],
            [
                10,
                4,
                "A350",
                "Alpha",
                "Alpha",
                true,
                1055
            ],
            [
                11,
                4,
                "C1350",
                "Gamma",
                "Gamma",
                true,
                1102
            ],
            [
                12,
                4,
                "B750",
                "Beta",
                "Beta",
                true,
                982
            ],
            [
                13,
                4,
                "B550",
                "Beta",
                "Beta",
                true,
                879
            ],
            [
                14,
                4,
                "A50",
                "Alpha",
                "Alpha",
                true,
                1222
            ]
        ],
        "typicality2": [
            [
                "trial",
                "block",
                "stimId",
                "category",
                "response",
                "rt"
            ],
            [
                0,
                0,
                "B750",
                "Beta",
                5,
                12220
            ],
            [
                1,
                0,
                "C1250",
                "Gamma",
                6,
                3810
            ],
            [
                2,
                0,
                "A250",
                "Alpha",
                6,
                5890
            ],
            [
                3,
                0,
                "A350",
                "Alpha",
                3,
                7209
            ],
            [
                4,
                0,
                "A50",
                "Alpha",
                6,
                7308
            ],
            [
                5,
                0,
                "A450",
                "Alpha",
                2,
                9604
            ],
            [
                6,
                0,
                "C1450",
                "Gamma",
                6,
                3788
            ],
            [
                7,
                0,
                "A150",
                "Alpha",
                6,
                6388
            ],
            [
                8,
                0,
                "B850",
                "Beta",
                5,
                8676
            ],
            [
                9,
                0,
                "B550",
                "Beta",
                6,
                4524
            ],
            [
                10,
                0,
                "B650",
                "Beta",
                6,
                2732
            ],
            [
                11,
                0,
                "C1350",
                "Gamma",
                6,
                1831
            ],
            [
                12,
                0,
                "C1150",
                "Gamma",
                6,
                1248
            ],
            [
                13,
                0,
                "B950",
                " Beta",
                3,
                4881
            ],
            [
                14,
                0,
                "C1050",
                "Gamma",
                4,
                4444
            ]
        ],
        "similarity": [
            [
                "trial",
                "block",
                "stimId1",
                "stimID2",
                "category1",
                "category2",
                "response",
                "rt"
            ],
            [
                1,
                0,
                "C1350",
                "C1250",
                "Gamma",
                "Gamma",
                5,
                12246
            ],
            [
                2,
                0,
                "C1350",
                "C1050",
                "Gamma",
                "Gamma",
                4,
                5535
            ],
            [
                3,
                0,
                "C1350",
                "A150",
                "Gamma",
                "Alpha",
                0,
                4650
            ],
            [
                4,
                0,
                "C1350",
                "A450",
                "Gamma",
                "Alpha",
                2,
                3581
            ],
            [
                5,
                0,
                "C1350",
                "C1150",
                "Gamma",
                "Gamma",
                5,
                4419
            ],
            [
                6,
                0,
                "C1350",
                "C1450",
                "Gamma",
                "Gamma",
                6,
                3266
            ],
            [
                7,
                0,
                "C1350",
                "B850",
                "Gamma",
                "Beta",
                3,
                4410
            ],
            [
                8,
                0,
                "C1350",
                "A350",
                "Gamma",
                "Alpha",
                0.9999999999999998,
                4165
            ],
            [
                9,
                0,
                "C1350",
                "A250",
                "Gamma",
                "Alpha",
                0.9999999999999998,
                1921
            ],
            [
                10,
                0,
                "C1350",
                "B650",
                "Gamma",
                "Beta",
                2,
                4506
            ],
            [
                11,
                0,
                "C1350",
                "B550",
                "Gamma",
                "Beta",
                2,
                1837
            ],
            [
                12,
                0,
                "C1350",
                "B750",
                "Gamma",
                "Beta",
                3,
                2287
            ],
            [
                13,
                0,
                "C1350",
                "A50",
                "Gamma",
                "Alpha",
                0,
                2884
            ],
            [
                14,
                0,
                "C1350",
                "B950",
                "Gamma",
                " Beta",
                4,
                5863
            ],
            [
                2,
                1,
                "C1250",
                "C1050",
                "Gamma",
                "Gamma",
                5,
                2776
            ],
            [
                3,
                1,
                "C1250",
                "A150",
                "Gamma",
                "Alpha",
                0,
                3036
            ],
            [
                4,
                1,
                "C1250",
                "A450",
                "Gamma",
                "Alpha",
                0.9999999999999998,
                3208
            ],
            [
                5,
                1,
                "C1250",
                "C1150",
                "Gamma",
                "Gamma",
                6,
                2912
            ],
            [
                6,
                1,
                "C1250",
                "C1450",
                "Gamma",
                "Gamma",
                6,
                2179
            ],
            [
                7,
                1,
                "C1250",
                "B850",
                "Gamma",
                "Beta",
                4,
                4015
            ],
            [
                8,
                1,
                "C1250",
                "A350",
                "Gamma",
                "Alpha",
                2,
                2443
            ],
            [
                9,
                1,
                "C1250",
                "A250",
                "Gamma",
                "Alpha",
                2,
                2001
            ],
            [
                10,
                1,
                "C1250",
                "B650",
                "Gamma",
                "Beta",
                3,
                2482
            ],
            [
                11,
                1,
                "C1250",
                "B550",
                "Gamma",
                "Beta",
                3,
                2659
            ],
            [
                12,
                1,
                "C1250",
                "B750",
                "Gamma",
                "Beta",
                3,
                1823
            ],
            [
                13,
                1,
                "C1250",
                "A50",
                "Gamma",
                "Alpha",
                0,
                2866
            ],
            [
                14,
                1,
                "C1250",
                "B950",
                "Gamma",
                " Beta",
                5,
                3153
            ],
            [
                3,
                2,
                "C1050",
                "A150",
                "Gamma",
                "Alpha",
                0.9999999999999998,
                2378
            ],
            [
                4,
                2,
                "C1050",
                "A450",
                "Gamma",
                "Alpha",
                3,
                2876
            ],
            [
                5,
                2,
                "C1050",
                "C1150",
                "Gamma",
                "Gamma",
                6,
                2531
            ],
            [
                6,
                2,
                "C1050",
                "C1450",
                "Gamma",
                "Gamma",
                5,
                3786
            ],
            [
                7,
                2,
                "C1050",
                "B850",
                "Gamma",
                "Beta",
                6,
                3907
            ],
            [
                8,
                2,
                "C1050",
                "A350",
                "Gamma",
                "Alpha",
                2,
                5066
            ],
            [
                9,
                2,
                "C1050",
                "A250",
                "Gamma",
                "Alpha",
                2,
                1147
            ],
            [
                10,
                2,
                "C1050",
                "B650",
                "Gamma",
                "Beta",
                3,
                2220
            ],
            [
                11,
                2,
                "C1050",
                "B550",
                "Gamma",
                "Beta",
                3,
                1275
            ],
            [
                12,
                2,
                "C1050",
                "B750",
                "Gamma",
                "Beta",
                4,
                2571
            ],
            [
                13,
                2,
                "C1050",
                "A50",
                "Gamma",
                "Alpha",
                0,
                2506
            ],
            [
                14,
                2,
                "C1050",
                "B950",
                "Gamma",
                " Beta",
                6,
                3115
            ],
            [
                4,
                3,
                "A150",
                "A450",
                "Alpha",
                "Alpha",
                3,
                6419
            ],
            [
                5,
                3,
                "A150",
                "C1150",
                "Alpha",
                "Gamma",
                0.9999999999999998,
                11323
            ],
            [
                6,
                3,
                "A150",
                "C1450",
                "Alpha",
                "Gamma",
                0,
                4018
            ],
            [
                7,
                3,
                "A150",
                "B850",
                "Alpha",
                "Beta",
                2,
                2490
            ],
            [
                8,
                3,
                "A150",
                "A350",
                "Alpha",
                "Alpha",
                5,
                3875
            ],
            [
                9,
                3,
                "A150",
                "A250",
                "Alpha",
                "Alpha",
                6,
                2643
            ],
            [
                10,
                3,
                "A150",
                "B650",
                "Alpha",
                "Beta",
                3,
                2378
            ],
            [
                11,
                3,
                "A150",
                "B550",
                "Alpha",
                "Beta",
                2,
                4994
            ],
            [
                12,
                3,
                "A150",
                "B750",
                "Alpha",
                "Beta",
                0.9999999999999998,
                3034
            ],
            [
                13,
                3,
                "A150",
                "A50",
                "Alpha",
                "Alpha",
                5,
                3531
            ],
            [
                14,
                3,
                "A150",
                "B950",
                "Alpha",
                " Beta",
                0.9999999999999998,
                5975
            ],
            [
                5,
                4,
                "A450",
                "C1150",
                "Alpha",
                "Gamma",
                3,
                2370
            ],
            [
                6,
                4,
                "A450",
                "C1450",
                "Alpha",
                "Gamma",
                2,
                6844
            ],
            [
                7,
                4,
                "A450",
                "B850",
                "Alpha",
                "Beta",
                3,
                5138
            ],
            [
                8,
                4,
                "A450",
                "A350",
                "Alpha",
                "Alpha",
                6,
                6531
            ],
            [
                9,
                4,
                "A450",
                "A250",
                "Alpha",
                "Alpha",
                5,
                2299
            ],
            [
                10,
                4,
                "A450",
                "B650",
                "Alpha",
                "Beta",
                5,
                4172
            ],
            [
                11,
                4,
                "A450",
                "B550",
                "Alpha",
                "Beta",
                6,
                2047
            ],
            [
                12,
                4,
                "A450",
                "B750",
                "Alpha",
                "Beta",
                5,
                2723
            ],
            [
                13,
                4,
                "A450",
                "A50",
                "Alpha",
                "Alpha",
                0,
                3090
            ],
            [
                14,
                4,
                "A450",
                "B950",
                "Alpha",
                " Beta",
                3,
                7101
            ],
            [
                6,
                5,
                "C1150",
                "C1450",
                "Gamma",
                "Gamma",
                5,
                3305
            ],
            [
                7,
                5,
                "C1150",
                "B850",
                "Gamma",
                "Beta",
                5,
                1540
            ],
            [
                8,
                5,
                "C1150",
                "A350",
                "Gamma",
                "Alpha",
                2,
                3203
            ],
            [
                9,
                5,
                "C1150",
                "A250",
                "Gamma",
                "Alpha",
                2,
                1178
            ],
            [
                10,
                5,
                "C1150",
                "B650",
                "Gamma",
                "Beta",
                3,
                2873
            ],
            [
                11,
                5,
                "C1150",
                "B550",
                "Gamma",
                "Beta",
                3,
                1274
            ],
            [
                12,
                5,
                "C1150",
                "B750",
                "Gamma",
                "Beta",
                4,
                2146
            ],
            [
                13,
                5,
                "C1150",
                "A50",
                "Gamma",
                "Alpha",
                0,
                4515
            ],
            [
                14,
                5,
                "C1150",
                "B950",
                "Gamma",
                " Beta",
                4,
                7843
            ],
            [
                7,
                6,
                "C1450",
                "B850",
                "Gamma",
                "Beta",
                4,
                2681
            ],
            [
                8,
                6,
                "C1450",
                "A350",
                "Gamma",
                "Alpha",
                0.9999999999999998,
                4617
            ],
            [
                9,
                6,
                "C1450",
                "A250",
                "Gamma",
                "Alpha",
                0.9999999999999998,
                1682
            ],
            [
                10,
                6,
                "C1450",
                "B650",
                "Gamma",
                "Beta",
                3,
                3063
            ],
            [
                11,
                6,
                "C1450",
                "B550",
                "Gamma",
                "Beta",
                3,
                1114
            ],
            [
                12,
                6,
                "C1450",
                "B750",
                "Gamma",
                "Beta",
                4,
                2824
            ],
            [
                13,
                6,
                "C1450",
                "A50",
                "Gamma",
                "Alpha",
                0,
                3472
            ],
            [
                14,
                6,
                "C1450",
                "B950",
                "Gamma",
                " Beta",
                3,
                4741
            ],
            [
                8,
                7,
                "B850",
                "A350",
                "Beta",
                "Alpha",
                3,
                2430
            ],
            [
                9,
                7,
                "B850",
                "A250",
                "Beta",
                "Alpha",
                3,
                1099
            ],
            [
                10,
                7,
                "B850",
                "B650",
                "Beta",
                "Beta",
                5,
                2819
            ],
            [
                11,
                7,
                "B850",
                "B550",
                "Beta",
                "Beta",
                5,
                1587
            ],
            [
                12,
                7,
                "B850",
                "B750",
                "Beta",
                "Beta",
                6,
                2603
            ],
            [
                13,
                7,
                "B850",
                "A50",
                "Beta",
                "Alpha",
                0,
                3643
            ],
            [
                14,
                7,
                "B850",
                "B950",
                "Beta",
                " Beta",
                6,
                3855
            ],
            [
                9,
                8,
                "A350",
                "A250",
                "Alpha",
                "Alpha",
                6,
                2228
            ],
            [
                10,
                8,
                "A350",
                "B650",
                "Alpha",
                "Beta",
                4,
                3344
            ],
            [
                11,
                8,
                "A350",
                "B550",
                "Alpha",
                "Beta",
                5,
                3347
            ],
            [
                12,
                8,
                "A350",
                "B750",
                "Alpha",
                "Beta",
                3,
                3746
            ],
            [
                13,
                8,
                "A350",
                "A50",
                "Alpha",
                "Alpha",
                0.9999999999999998,
                3538
            ],
            [
                14,
                8,
                "A350",
                "B950",
                "Alpha",
                " Beta",
                3,
                4673
            ],
            [
                10,
                9,
                "A250",
                "B650",
                "Alpha",
                "Beta",
                4,
                2749
            ],
            [
                11,
                9,
                "A250",
                "B550",
                "Alpha",
                "Beta",
                4,
                1363
            ],
            [
                12,
                9,
                "A250",
                "B750",
                "Alpha",
                "Beta",
                4,
                659
            ],
            [
                13,
                9,
                "A250",
                "A50",
                "Alpha",
                "Alpha",
                3,
                2673
            ],
            [
                14,
                9,
                "A250",
                "B950",
                "Alpha",
                " Beta",
                0.9999999999999998,
                4315
            ],
            [
                11,
                10,
                "B650",
                "B550",
                "Beta",
                "Beta",
                6,
                3393
            ],
            [
                12,
                10,
                "B650",
                "B750",
                "Beta",
                "Beta",
                6,
                1576
            ],
            [
                13,
                10,
                "B650",
                "A50",
                "Beta",
                "Alpha",
                0,
                2808
            ],
            [
                14,
                10,
                "B650",
                "B950",
                "Beta",
                " Beta",
                4,
                4048
            ],
            [
                12,
                11,
                "B550",
                "B750",
                "Beta",
                "Beta",
                5,
                2116
            ],
            [
                13,
                11,
                "B550",
                "A50",
                "Beta",
                "Alpha",
                0.9999999999999998,
                2851
            ],
            [
                14,
                11,
                "B550",
                "B950",
                "Beta",
                " Beta",
                3,
                2619
            ],
            [
                13,
                12,
                "B750",
                "A50",
                "Beta",
                "Alpha",
                0,
                2347
            ],
            [
                14,
                12,
                "B750",
                "B950",
                "Beta",
                " Beta",
                5,
                6448
            ],
            [
                14,
                13,
                "A50",
                "B950",
                "Alpha",
                " Beta",
                0,
                3118
            ]
        ],
        "testPhase": [
            [
                "trial",
                "block",
                "stimId",
                "category",
                "response",
                "accuracy",
                "rt"
            ],
            [
                0,
                0,
                "C1350",
                "Gamma",
                "Gamma",
                true,
                2783
            ],
            [
                1,
                0,
                "T500",
                "test",
                "Beta",
                false,
                1967
            ],
            [
                2,
                0,
                "A250",
                "Alpha",
                "Alpha",
                true,
                1361
            ],
            [
                3,
                0,
                "C1450",
                "Gamma",
                "Gamma",
                true,
                1580
            ],
            [
                4,
                0,
                "A350",
                "Alpha",
                "Alpha",
                true,
                3103
            ],
            [
                5,
                0,
                "C1150",
                "Gamma",
                "Gamma",
                true,
                2364
            ],
            [
                6,
                0,
                "B550",
                "Beta",
                "Beta",
                true,
                884
            ],
            [
                7,
                0,
                "A150",
                "Alpha",
                "Alpha",
                true,
                992
            ],
            [
                8,
                0,
                "C1250",
                "Gamma",
                "Gamma",
                true,
                1657
            ],
            [
                9,
                0,
                "B950",
                " Beta",
                "Beta",
                false,
                1692
            ],
            [
                10,
                0,
                "A50",
                "Alpha",
                "Alpha",
                true,
                1572
            ],
            [
                11,
                0,
                "C1050",
                "Gamma",
                "Gamma",
                true,
                3883
            ],
            [
                12,
                0,
                "A450",
                "Alpha",
                "Beta",
                false,
                1468
            ],
            [
                13,
                0,
                "B650",
                "Beta",
                "Beta",
                true,
                1766
            ],
            [
                14,
                0,
                "B850",
                "Beta",
                "Beta",
                true,
                1143
            ],
            [
                15,
                0,
                "T1000",
                "test",
                "Gamma",
                false,
                1332
            ],
            [
                16,
                0,
                "B750",
                "Beta",
                "Beta",
                true,
                991
            ]
        ]
    }
}